sortinpy/__init__.py
sortinpy/_make_stats.py
sortinpy/binary_search.py
sortinpy/bogo_sort.py
sortinpy/bubble_sort.py
sortinpy/counting_sort.py
sortinpy/heap_sort.py
sortinpy/insertion_sort.py
sortinpy/introsort.py
sortinpy/linear_search.py
sortinpy/lower_bound.py
sortinpy/merge_sort.py
sortinpy/quick_sort.py
sortinpy/radix_sort.py
sortinpy/selection_sort.py
sortinpy/shell_sort.py
sortinpy/upper_bound.py
sortinpy-0.1.0.dist-info/licenses/LICENSE
sortinpy-0.1.0.dist-info/METADATA
sortinpy-0.1.0.dist-info/WHEEL
sortinpy-0.1.0.dist-info/top_level.txt
sortinpy-0.1.0.dist-info/RECORD
