Metadata-Version: 2.4
Name: sortinpy
Version: 0.1.0
Summary: Pacote Python com vários algoritmos de ordenação e busca
Home-page: 
Author: wandsondev
Author-email: wandsondev@gmail.com
Classifier: Programming Language :: Python :: 3
Classifier: License :: OSI Approved :: MIT License
Classifier: Operating System :: OS Independent
Requires-Python: >=3.6
License-File: LICENSE
Dynamic: author
Dynamic: author-email
Dynamic: classifier
Dynamic: description
Dynamic: description-content-type
Dynamic: license-file
Dynamic: requires-python
Dynamic: summary
